LICENSE
README.md
VERSION
requirements.txt
setup.py
texta_face_analyzer/__init__.py
texta_face_analyzer/face_analyzer.py
texta_face_analyzer.egg-info/PKG-INFO
texta_face_analyzer.egg-info/SOURCES.txt
texta_face_analyzer.egg-info/dependency_links.txt
texta_face_analyzer.egg-info/requires.txt
texta_face_analyzer.egg-info/top_level.txt