Metadata-Version: 2.1
Name: texta-face-analyzer
Version: 0.1.9
Summary: TEXTA's interface for identiying and comparing facial encodings.
Home-page: https://git.texta.ee/texta/texta-face-analyzer-python
Author: TEXTA
Author-email: info@texta.ee
License: GPLv3
Platform: UNKNOWN
